grid_indexing-0.1.1.dist-info/METADATA
grid_indexing-0.1.1.dist-info/WHEEL
grid_indexing-0.1.1.dist-info/licenses/LICENSE
grid_indexing/grids.py
grid_indexing/tutorial.py
grid_indexing/tests/__init__.py
grid_indexing/tests/test_rtree.py
grid_indexing/tests/test_grids.py
grid_indexing/tests/test_distributed.py
grid_indexing/__init__.py
grid_indexing/distributed.py
grid_indexing/grid_indexing.cpython-311-darwin.so
grid_indexing-0.1.1.dist-info/RECORD
